{"skeleton":{"width":207.1,"height":295.52,"hash":" ","name":"armatureName"},"bones":[{"name":"root"},{"length":52,"rotation":90,"name":"C","parent":"root"},{"x":152.1315,"y":2.3041,"rotation":-90,"name":"C_Hip","parent":"C"},{"x":34.9205,"y":83.8386,"rotation":-90,"name":"IK_C_L_Leg","parent":"C"},{"x":42.3305,"y":-74.5012,"rotation":-90,"name":"IK_C_R_Leg","parent":"C"},{"length":38,"x":-38.7039,"y":2.392,"rotation":-127.8682,"name":"C_L_Skirt_I","parent":"C_Hip"},{"length":47,"x":5.5358,"y":-12.2299,"rotation":-94.8079,"name":"C_B_Skirt","parent":"C_Hip"},{"length":46,"x":-11.444,"y":16.961,"rotation":98.6371,"name":"C_Chest","parent":"C_Hip"},{"length":43,"x":-0.592,"y":-8.4719,"rotation":-108.4802,"name":"C_L_Skirt_II","parent":"C_Hip"},{"length":44,"x":6.304,"y":-18.152,"rotation":-55.2467,"name":"C_R_Thigh","parent":"C_Hip"},{"length":41,"x":4.4079,"y":-21.704,"rotation":-75.2049,"name":"C_R_Skirt_II","parent":"C_Hip"},{"length":53,"x":-33.316,"y":-7.268,"rotation":-101.2508,"name":"C_L_Thigh","parent":"C_Hip"},{"length":37,"x":16.2719,"y":-9.928,"rotation":-47.8208,"name":"C_R_Skirt_I","parent":"C_Hip"},{"y":-26.9099,"name":"IK_C_L_Foot","parent":"IK_C_L_Leg"},{"x":-1.17,"y":-33.5399,"name":"IK_C_R_Foot","parent":"IK_C_R_Leg"},{"length":41,"x":44.8326,"y":32.3176,"rotation":167.3904,"name":"C_L_Arm","parent":"C_Chest"},{"length":67,"x":53.1184,"y":-0.1921,"rotation":-22.3993,"name":"C_L_Calf","parent":"C_L_Thigh"},{"length":32,"x":30.6016,"y":-30.7928,"rotation":175.8524,"name":"C_R_Arm","parent":"C_Chest"},{"length":92,"x":47.8158,"y":-9.5167,"rotation":-8.6371,"name":"C_Head","parent":"C_Chest"},{"length":45,"x":37.4648,"y":-0.1934,"rotation":2.4423,"name":"C_L_Skirt_I2","parent":"C_L_Skirt_I"},{"length":46,"x":41.6675,"rotation":-11.7705,"name":"C_R_Skirt_II2","parent":"C_R_Skirt_II"},{"length":53,"x":43.8706,"rotation":9.4251,"name":"C_L_Skirt_II2","parent":"C_L_Skirt_II"},{"length":72,"x":44.2671,"y":0.0922,"rotation":6.8645,"name":"C_R_Calf","parent":"C_R_Thigh"},{"length":62,"x":47.2462,"rotation":-1.7119,"name":"C_B_Skirt2","parent":"C_B_Skirt"},{"length":49,"x":37.2311,"rotation":-7.2252,"name":"C_R_Skirt_I2","parent":"C_R_Skirt_I"},{"x":81.2159,"y":-25.3439,"rotation":-3.2195,"name":"C_Hood_I","parent":"C_Head"},{"length":35,"x":33.8332,"y":-1.8485,"rotation":33.7474,"name":"C_L_Forearm","parent":"C_L_Arm"},{"length":36,"x":71.958,"y":0.0142,"rotation":-42.5306,"name":"C_R_Foot","parent":"C_R_Calf"},{"length":26,"x":39.5329,"y":-3.686,"rotation":50.2984,"name":"C_R_Forearm","parent":"C_R_Arm"},{"length":31,"x":67.261,"y":0.0873,"rotation":33.6501,"name":"C_L_Foot","parent":"C_L_Calf"},{"length":60,"x":56.4479,"y":52.9919,"rotation":-176.6981,"name":"C_Hood_II","parent":"C_Head"},{"length":26,"x":32.8897,"y":9.52,"rotation":53.5979,"name":"C_L_Hand","parent":"C_L_Forearm"},{"length":35,"x":29.5264,"y":2.0331,"rotation":35.0826,"name":"C_R_Hand","parent":"C_R_Forearm"},{"length":59,"x":4.7737,"y":24.5826,"rotation":157.7782,"name":"C_R_Shield","parent":"C_R_Hand"},{"length":75,"x":3.7088,"y":13.2845,"rotation":169.2339,"name":"C_L_Shield","parent":"C_L_Hand"},{"x":35.7138,"y":-6.2347,"rotation":-7.2783,"name":"Muzzle","parent":"C_L_Hand"}],"slots":[{"name":"C_R_Arm","bone":"C_R_Arm","attachment":"C_R_Arm"},{"name":"C_R_Forearm","bone":"C_R_Forearm","attachment":"C_R_Forearm"},{"name":"C_R_Hand","bone":"C_R_Hand","attachment":"C_R_Hand"},{"name":"C_R_Shield","bone":"C_R_Shield","attachment":"C_R_Shield"},{"name":"C_R_Calf","bone":"C_R_Calf","attachment":"C_R_Calf"},{"name":"C_R_Thigh","bone":"C_R_Thigh","attachment":"C_R_Thigh"},{"name":"C_R_Foot","bone":"C_R_Foot","attachment":"C_R_Foot"},{"name":"C_L_Calf","bone":"C_L_Calf","attachment":"C_L_Calf"},{"name":"C_L_Thigh","bone":"C_L_Thigh","attachment":"C_L_Thigh"},{"name":"C_L_Foot","bone":"C_L_Foot","attachment":"C_L_Foot"},{"name":"C_B_Skirt","bone":"C_B_Skirt","attachment":"C_B_Skirt"},{"name":"C_R_Skirt","bone":"C_R_Skirt_I","attachment":"C_R_Skirt"},{"name":"C_L_Skirt","bone":"C_L_Skirt_I","attachment":"C_L_Skirt"},{"name":"C_Waist","bone":"C_Hip","attachment":"C_Waist"},{"name":"C_Bag","bone":"C_Hip","attachment":"C_Bag"},{"name":"C_B_Hood","bone":"C_Head","attachment":"C_B_Hood"},{"name":"C_Chest","bone":"C_Chest","attachment":"C_Chest"},{"name":"C_Face","bone":"C_Head","attachment":"C_Face"},{"name":"C_Scarf","bone":"C_Chest","attachment":"C_Scarf"},{"name":"C_A_Hood","bone":"C_Hood_I","attachment":"C_A_Hood"},{"name":"C_L_Arm","bone":"C_L_Arm","attachment":"C_L_Arm"},{"name":"C_L_Forearm","bone":"C_L_Forearm","attachment":"C_L_Forearm"},{"name":"C_L_Hand","bone":"C_L_Hand","attachment":"C_L_Hand"},{"name":"C_L_Shield","bone":"C_L_Shield","attachment":"C_L_Shield"}],"ik":[{"name":"IK_C_R_Leg","target":"IK_C_R_Leg","bones":["C_R_Thigh","C_R_Calf"]},{"bendPositive":false,"name":"IK_C_L_Leg","target":"IK_C_L_Leg","bones":["C_L_Thigh","C_L_Calf"]},{"name":"IK_C_R_Foot","target":"IK_C_R_Foot","bones":["C_R_Foot"]},{"name":"IK_C_L_Foot","target":"IK_C_L_Foot","bones":["C_L_Foot"]}],"skins":{"default":{"C_B_Hood":{"C_B_Hood":{"name":"C_B_Hood","width":72,"height":52,"x":43.46,"y":-2.75,"rotation":-90,"scaleX":2,"scaleY":2}},"C_L_Hand":{"C_L_Hand":{"name":"C_L_Hand","width":40,"height":31,"x":19.92,"y":-4.6,"rotation":6.63,"scaleX":2,"scaleY":2}},"C_Waist":{"C_Waist":{"name":"C_Waist","width":38,"height":19,"x":-15.47,"y":8.12,"scaleX":2,"scaleY":2}},"C_L_Arm":{"C_L_Arm":{"name":"C_L_Arm","width":18,"height":23,"x":15.3,"y":0.72,"rotation":93.97,"scaleX":2,"scaleY":2}},"C_L_Forearm":{"C_L_Forearm":{"name":"C_L_Forearm","width":24,"height":31,"x":16.03,"y":0.45,"rotation":60.23,"scaleX":2,"scaleY":2}},"C_A_Hood":{"C_A_Hood":{"name":"C_A_Hood","width":92,"height":91,"hull":27,"triangles":[18,33,19,19,22,20,22,21,20,33,22,19,34,33,18,17,34,18,33,23,22,24,23,33,34,24,33,35,32,34,25,24,34,32,25,34,17,35,34,32,31,25,16,35,17,16,32,35,31,0,26,25,31,26,16,15,32,15,14,32,32,30,31,30,0,31,13,30,32,14,13,32,4,3,2,1,36,2,36,4,2,0,36,1,30,36,0,13,28,30,30,28,36,28,37,36,37,4,36,37,5,4,13,12,28,27,37,28,27,9,37,37,29,5,29,8,6,8,7,6,5,29,6,11,27,28,12,11,28,9,29,37,9,8,29,10,9,27,11,10,27],"uvs":[0.49761,0.52803,0.52377,0.64011,0.54305,0.78142,0.39502,0.81345,0.38219,0.78071,0.26239,0.81343,0.26514,0.88583,0.10954,1,0.09646,0.87191,0.12744,0.66098,0,0.5956,0.07582,0.44871,0.14259,0.34785,0.19704,0.2656,0.33157,0.04699,0.40937,0,0.59217,0.06904,0.74541,0.1555,0.88036,0.26479,0.9481,0.45699,1,0.61362,0.92756,0.75542,0.87454,0.51734,0.78228,0.45817,0.76576,0.4171,0.67005,0.44216,0.66937,0.47906,0.15446,0.52479,0.2328,0.48328,0.2063,0.80951,0.36492,0.47227,0.60752,0.43716,0.58759,0.25955,0.84424,0.39055,0.79067,0.28222,0.70096,0.19782,0.39674,0.65527,0.21708,0.69623],"edges":[0,2,2,4,4,6,6,8,8,10,10,12,12,14,14,16,16,18,18,20,20,22,22,24,24,26,26,28,28,30,30,32,32,34,34,36,36,38,38,40,40,42,42,44,44,46,46,48,48,50,50,52,52,0],"vertices":[3,18,44.38,11.69,0.27537,25,-38.85,34.91,0.36112,30,14.42,40.54,0.36352,3,18,24.09,6.9,0.26322,25,-58.84,28.99,0.11112,30,34.95,44.15,0.62566,2,18,-1.49,3.37,0.18381,30,60.69,46.2,0.81619,2,18,-7.29,30.46,0.08674,30,64.93,18.82,0.91326,2,18,-1.36,32.81,0.10334,30,58.87,16.82,0.89666,2,18,-7.28,54.73,0.02303,30,63.52,-5.41,0.97697,2,18,-20.39,54.23,0.00367,30,76.63,-5.66,0.99633,1,30,95.62,-35.28,1,2,18,-17.86,85.1,0.055,30,72.33,-36.33,0.945,2,18,20.31,79.43,0.30458,30,34.55,-28.48,0.69542,2,18,32.15,102.75,0.495,30,21.39,-51.07,0.505,2,18,58.73,88.87,0.71667,30,-4.35,-35.69,0.28333,2,18,76.99,76.66,0.80083,30,-21.88,-22.45,0.19917,2,18,91.88,66.69,0.9302,30,-36.17,-11.63,0.0698,2,18,131.45,42.07,0.97373,30,-74.25,15.22,0.02627,2,18,139.96,27.83,0.96059,30,-81.93,29.93,0.03941,2,18,127.46,-5.62,0.97373,30,-67.52,62.61,0.02627,2,18,111.81,-33.66,0.98686,30,-50.28,89.7,0.01314,1,18,92.03,-58.36,1,1,18,57.24,-70.75,1,1,18,28.89,-80.25,1,2,18,3.22,-66.99,0.88889,25,-75.53,-45.96,0.11111,2,18,46.31,-57.29,0.63889,25,-33.05,-33.86,0.36111,2,18,57.03,-40.41,0.22917,25,-23.3,-16.4,0.77083,2,18,64.46,-37.38,0.08333,25,-16.05,-12.96,0.91667,3,18,59.92,-19.87,0.05726,25,-21.56,4.27,0.91667,30,0.73,72.94,0.02607,3,18,53.24,-19.74,0.17261,25,-28.24,4.02,0.71834,30,7.39,72.43,0.10905,2,18,44.97,74.48,0.51611,30,10.22,-22.11,0.48389,2,18,52.47,60.15,0.275,30,3.55,-7.37,0.725,2,18,-6.57,65,0.07333,30,62.22,-15.62,0.92667,2,18,54.47,35.97,0.33131,30,2.95,16.88,0.66869,3,18,60.83,-8.42,0.23226,25,-21.3,15.75,0.74167,30,-0.84,61.56,0.02607,2,18,92.97,-4.78,0.2625,25,10.59,21.19,0.7375,2,18,69.26,-51.75,0.15333,25,-10.45,-27.04,0.84667,2,18,88.87,-41.94,0.175,25,8.58,-16.14,0.825,2,18,104.15,-25.52,0.2625,25,22.91,1.11,0.7375,2,18,21.35,30.14,0.23902,30,36.35,20.79,0.76098,2,18,13.93,63.02,0.18333,30,41.86,-12.46,0.81667],"type":"mesh"}},"C_Scarf":{"C_Scarf":{"name":"C_Scarf","width":61,"height":30,"hull":9,"triangles":[6,9,7,7,0,8,9,0,7,0,2,1,9,2,0,6,10,9,10,3,9,5,10,6,5,4,3,5,3,10,9,3,2],"uvs":[0.87532,0.4632,0.91623,0.72422,0.62987,1,0.09351,0.48651,0.03214,0.72888,0,0.41193,0.11396,0,0.94351,0,1,0.20684,0.51396,0.39328,0.08214,0.36998],"edges":[0,2,2,4,4,6,6,8,8,10,10,12,12,14,14,16,16,0],"vertices":[2,7,33.79,-56.1,0.44,18,-6.88,-48.16,0.56,1,7,17.82,-58.68,1,1,7,6.94,-21.98,1,1,7,46.64,37.63,1,1,7,33.61,47.12,1,2,7,52.68,48.16,0.44,18,-3.86,57.75,0.56,1,18,20.46,43.96,1,1,18,20.46,-56.41,1,1,18,8.25,-63.25,1,2,7,44.43,-13.49,0.44,18,-2.76,-4.44,0.56,2,7,53.64,37.96,0.44,18,-1.38,47.81,0.56],"type":"mesh"}},"C_L_Shield":{"C_L_Shield":{"name":"C_L_Shield","width":74,"height":37,"x":47.7,"y":9.84,"rotation":-162.61,"scaleX":2,"scaleY":2}},"C_Face":{"C_Face":{"name":"C_Face","width":60,"height":57,"x":48.46,"y":-4.25,"rotation":-90,"scaleX":2,"scaleY":2}},"C_R_Arm":{"C_R_Arm":{"name":"C_R_Arm","width":16,"height":29,"x":16.45,"y":2.35,"rotation":85.51,"scaleX":2,"scaleY":2}},"C_L_Calf":{"C_L_Calf":{"name":"C_L_Calf","width":37,"height":48,"x":36.85,"y":-0.22,"rotation":123.65,"scaleX":2,"scaleY":2}},"C_Bag":{"C_Bag":{"name":"C_Bag","width":42,"height":23,"x":-0.97,"y":-1.88,"scaleX":2,"scaleY":2}},"C_R_Foot":{"C_R_Foot":{"name":"C_R_Foot","width":33,"height":28,"x":14.56,"y":3.85,"rotation":90.91,"scaleX":2,"scaleY":2}},"C_R_Thigh":{"C_R_Thigh":{"name":"C_R_Thigh","width":25,"height":31,"x":17.2,"y":-1.92,"rotation":55.25,"scaleX":2,"scaleY":2}},"C_L_Skirt":{"C_L_Skirt":{"name":"C_L_Skirt","width":57,"height":68,"hull":13,"triangles":[9,14,8,14,7,8,14,9,10,11,12,10,12,14,10,0,1,12,1,13,12,12,13,14,13,5,14,14,5,7,5,6,7,3,4,13,1,2,13,4,5,13,2,3,13],"uvs":[0.5043,0,0.35664,0.17108,0.19464,0.35095,0,0.61809,0.12031,0.80391,0.40235,0.92237,0.74498,1,0.76362,0.87472,1,0.7572,1,0.48716,1,0.25012,1,0.11432,0.66679,0,0.43192,0.46746,0.75388,0.538],"edges":[0,2,2,4,4,6,6,8,8,10,10,12,12,14,14,16,16,18,18,20,20,22,22,24,24,0],"vertices":[3,19,-47.93,-9.7,0.01365,5,-10.01,-11.93,0.31969,2,-41.98,17.62,0.66667,3,19,-19.3,-9.81,0.34698,5,18.6,-10.82,0.31969,2,-58.67,-5.65,0.33333,4,19,11.24,-10.55,0.57438,5,49.15,-10.25,0.35346,21,-9.89,-64.83,0.05099,8,44.73,-65.58,0.02117,2,19,53.6,-7.42,0.93188,21,29.45,-80.84,0.06812,3,19,66.31,18.31,0.6874,5,102.94,20.92,0.00002,21,52.27,-63.44,0.31258,3,19,60.96,53.62,0.35421,5,96.09,55.98,0.00002,21,63.16,-29.42,0.64577,3,19,47.12,91.29,0.08885,5,80.65,93.03,0.00002,21,67.49,10.48,0.91113,2,21,50.34,9.87,0.99495,8,91.91,17.98,0.00505,2,21,30.35,33.73,0.77238,8,68.29,38.24,0.22762,2,21,-5.92,27.95,0.57623,8,33.45,26.6,0.42377,3,21,-37.76,22.87,0.11076,8,2.88,16.38,0.55591,2,14.03,-16.39,0.33333,2,8,-14.63,10.53,0.33333,2,14.03,2.07,0.66667,1,2,-23.62,17.62,1,4,19,8.61,20.48,0.41901,5,45.19,20.64,0.15159,21,1.53,-35.86,0.39709,8,51.26,-35.13,0.03231,4,19,-4.66,55.69,0.08568,5,30.44,55.25,0.15159,21,5.29,1.57,0.50785,8,48.83,2.42,0.25488],"type":"mesh"}},"C_R_Calf":{"C_R_Calf":{"name":"C_R_Calf","width":43,"height":44,"x":44.06,"y":1.55,"rotation":48.38,"scaleX":2,"scaleY":2}},"C_R_Shield":{"C_R_Shield":{"name":"C_R_Shield","width":69,"height":30,"x":39.16,"y":4.46,"rotation":-157.65,"scaleX":2,"scaleY":2}},"C_R_Skirt":{"C_R_Skirt":{"name":"C_R_Skirt","width":50,"height":61,"hull":13,"triangles":[14,7,8,9,14,8,14,6,7,13,6,14,10,14,9,13,4,6,10,13,14,1,13,10,12,1,10,4,5,6,11,12,10,0,1,12,2,3,4,2,4,13,1,2,13],"uvs":[0.07671,0.10559,0.04789,0.33931,0.02852,0.54449,0.00617,0.8034,0.25649,0.83638,0.29373,1,0.59322,0.88767,0.85138,0.76432,0.99999,0.64219,0.79625,0.41259,0.58318,0.19031,0.39963,0,0.23722,0.07037,0.33213,0.54986,0.65603,0.46892],"edges":[0,2,2,4,4,6,6,8,8,10,10,12,12,14,14,16,16,18,18,20,20,22,22,24,24,0],"vertices":[3,10,-16.2,-14.55,0.32077,20,-53.68,-26.05,0.01256,2,-13.8,-9.76,0.66667,3,10,10.63,-24.62,0.49168,20,-25.36,-30.43,0.17499,2,-16.68,-38.27,0.33333,2,10,34.34,-32.88,0.44556,20,-0.47,-33.69,0.55444,2,10,64.31,-43.11,0.18723,20,30.96,-37.58,0.81277,2,10,74.59,-19.93,0.01632,20,36.3,-12.8,0.98368,3,10,94.84,-21.42,0.00031,20,56.43,-10.13,0.93661,24,47.57,-73.95,0.06308,2,20,44.33,20.5,0.6524,24,53.5,-41.57,0.3476,2,20,30.66,47.07,0.31907,24,55.95,-11.78,0.68093,2,20,16.56,62.7,0.04881,24,52.25,8.94,0.95119,4,10,38.39,45.46,0.01078,20,-12.48,43.84,0.01488,12,55.76,6.01,0.25016,24,17.62,8.29,0.72418,3,12,21.36,8.42,0.33333,24,-16.81,6.36,0.33333,2,36.85,-20.1,0.33333,2,12,-8.18,10.41,0.33333,2,18.49,3.12,0.66667,1,2,2.26,-5.47,1,4,10,42.73,-3.7,0.27167,20,1.79,-3.4,0.4292,12,37,-39.64,0.00021,24,4.76,-39.35,0.29891,4,10,41.45,30.14,0.10077,20,-6.36,29.46,0.26678,12,51.43,-9,0.00021,24,15.22,-7.14,0.63225],"type":"mesh"}},"C_B_Skirt":{"C_B_Skirt":{"name":"C_B_Skirt","width":31,"height":49,"hull":10,"triangles":[11,4,5,10,11,7,7,11,6,11,5,6,10,7,8,9,10,8,2,11,10,1,10,9,0,1,9,3,4,11,2,3,11,1,2,10],"uvs":[0.18934,0,0.15116,0.28832,0.04087,0.60767,0,0.96192,0.46506,0.98875,0.90622,0.98875,0.95712,0.7016,0.97409,0.44665,1,0.17292,0.63898,0.05215,0.55414,0.36883,0.50324,0.67745],"edges":[0,2,2,4,4,6,6,8,8,10,10,12,12,14,14,16,16,18,18,0],"vertices":[2,23,-22.46,-27.53,0.23483,6,23.98,-26.85,0.76517,2,23,5.89,-26.68,0.56815,6,52.34,-26.84,0.43185,2,23,37.76,-29.91,0.89101,6,84.1,-31.02,0.10899,2,23,72.54,-28.49,0.99999,6,118.9,-30.64,0.00001,1,23,71.88,0.46,1,1,23,68.77,27.63,1,2,23,40.46,27.57,0.9736,6,88.51,26.35,0.0264,2,23,15.51,25.79,0.72638,6,63.52,25.31,0.27362,2,23,-11.31,24.33,0.39304,6,36.66,24.66,0.60696,2,23,-20.54,0.75,0.32237,6,26.74,1.36,0.67763,2,23,10.89,-0.95,0.66657,6,58.1,-1.28,0.33343,2,23,41.3,-0.66,0.99991,6,88.51,-1.89,0.00009],"type":"mesh"}},"C_R_Hand":{"C_R_Hand":{"name":"C_R_Hand","width":36,"height":28,"x":25.42,"y":-2.1,"rotation":0.13,"scaleX":2,"scaleY":2}},"C_R_Forearm":{"C_R_Forearm":{"name":"C_R_Forearm","width":21,"height":20,"x":13.83,"y":-1.89,"rotation":35.21,"scaleX":2,"scaleY":2}},"C_L_Foot":{"C_L_Foot":{"name":"C_L_Foot","width":32,"height":28,"x":7.51,"y":4.6,"rotation":90,"scaleX":2,"scaleY":2}},"C_L_Thigh":{"C_L_Thigh":{"name":"C_L_Thigh","width":17,"height":36,"x":23.97,"y":3.09,"rotation":101.25,"scaleX":2,"scaleY":2}},"C_Chest":{"C_Chest":{"name":"C_Chest","width":39,"height":27,"x":25.33,"y":-0.79,"rotation":-98.64,"scaleX":2,"scaleY":2}}}},"animations":{"Attack":{"bones":{"C_L_Skirt_I":{"rotate":[{"time":0,"curve":[0.25,0,0.75,1],"angle":-5.99},{"time":0.3333,"curve":"stepped","angle":-7.91},{"time":0.6666,"curve":[0.0916771,0.386666656,0.404568225,0.9866667],"angle":-7.91},{"time":0.7333,"curve":[0.504276156,0.008888889,0.8219649,0.9955556],"angle":-21.91},{"time":1.1666,"angle":-5.99}],"shear":[{"time":0,"curve":[0.25,0,0.75,1]},{"time":0.3333,"curve":"stepped"},{"time":0.6666,"curve":[0.0916771,0.386666656,0.404568225,0.9866667]},{"time":0.7333,"curve":[0.504276156,0.008888889,0.8219649,0.9955556]},{"time":1.1666}]},"C_R_Hand":{"rotate":[{"time":0,"curve":[0.25,0,0.625,0.5],"angle":0},{"time":0.3333,"curve":"stepped","angle":-38.06},{"time":0.6666,"curve":[0.259595335,0.5688889,0.5245098,0.9911111],"angle":-38.06},{"time":0.6999,"curve":[0.25,0,0.75,1],"angle":-38.41},{"time":0.8999,"curve":[0.576241136,0.008888889,0.855548561,1],"angle":-7.04},{"time":1.1666,"angle":0}],"shear":[{"time":0,"curve":[0.25,0,0.625,0.5]},{"time":0.3333,"curve":"stepped"},{"time":0.6666,"curve":[0.259595335,0.5688889,0.5245098,0.9911111]},{"time":0.6999,"curve":[0.25,0,0.75,1]},{"time":0.8999,"curve":[0.576241136,0.008888889,0.855548561,1]},{"time":1.1666}]},"IK_C_R_Leg":{"translate":[{"time":0,"curve":[0.25,0,0.75,1]},{"time":0.3333,"curve":"stepped","y":-16.59},{"time":0.6666,"curve":[0.259595335,0.5688889,0.5245098,0.9911111],"y":-16.59},{"time":0.6999,"curve":[0.576241136,0.008888889,0.855548561,1],"y":14.92},{"time":1.1666}]},"C_Hip":{"translate":[{"time":0,"curve":[0.25,0,0.75,1]},{"time":0.3333,"curve":"stepped","x":-5.35,"y":-10.16},{"time":0.6666,"curve":[0.259595335,0.5688889,0.5245098,0.9911111],"x":-5.35,"y":-10.16},{"time":0.6999,"curve":[0.576241136,0.008888889,0.855548561,1],"x":-4.88,"y":12.93},{"time":1.1666}],"rotate":[{"time":0,"angle":0.22}],"shear":[{"time":0}]},"C_R_Skirt_II2":{"rotate":[{"time":0,"curve":[0.25,0,0.75,1],"angle":2.47},{"time":0.3333,"curve":"stepped","angle":0.66},{"time":0.6666,"curve":[0.0916771,0.386666656,0.404568225,0.9866667],"angle":0.66},{"time":0.6999,"curve":[0.25,0.311111122,0.74999994,1],"angle":-4.59},{"time":0.8666,"curve":[0.504276156,0.008888889,0.8219649,0.9955556],"angle":16.43},{"time":1.1666,"angle":2.47}],"shear":[{"time":0,"curve":[0.25,0,0.75,1]},{"time":0.3333,"curve":"stepped"},{"time":0.6666,"curve":[0.0916771,0.386666656,0.404568225,0.9866667]},{"time":0.6999,"curve":[0.25,0.311111122,0.74999994,1]},{"time":0.8666,"curve":[0.504276156,0.008888889,0.8219649,0.9955556]},{"time":1.1666}]},"C_L_Shield":{"rotate":[{"time":0,"curve":"stepped","angle":0},{"time":0.6667,"curve":[0.259595335,0.5688889,0.5245098,0.9911111],"angle":0},{"time":0.7,"curve":[0.25,0,0.75,1],"angle":8.64},{"time":0.9,"curve":[0.576241136,0.008888889,0.855548561,1],"angle":-22.4},{"time":1.1667,"angle":0}],"shear":[{"time":0,"curve":"stepped"},{"time":0.6667,"curve":[0.259595335,0.5688889,0.5245098,0.9911111]},{"time":0.7,"curve":[0.25,0,0.75,1]},{"time":0.9,"curve":[0.576241136,0.008888889,0.855548561,1]},{"time":1.1667}]},"C_L_Skirt_I2":{"rotate":[{"time":0,"curve":[0.25,0,0.75,1],"angle":-6.21},{"time":0.3333,"curve":"stepped","angle":7.11},{"time":0.6666,"curve":[0.0916771,0.386666656,0.404568225,0.9866667],"angle":7.11},{"time":0.6999,"curve":[0.245202333,0.364444435,0.74999994,1],"angle":12.55},{"time":0.8332,"curve":[0.504276156,0.008888889,0.8219649,0.9955556],"angle":-37.85},{"time":1.1665,"angle":-6.21}],"shear":[{"time":0,"curve":[0.25,0,0.75,1]},{"time":0.3333,"curve":"stepped"},{"time":0.6666,"curve":[0.0916771,0.386666656,0.404568225,0.9866667]},{"time":0.6999,"curve":[0.245202333,0.364444435,0.74999994,1]},{"time":0.8332,"curve":[0.504276156,0.008888889,0.8219649,0.9955556]},{"time":1.1665}]},"C_Hood_I":{"translate":[{"time":0,"curve":"stepped","x":-1.29,"y":1.01},{"time":0.6667,"curve":[0.206821024,0.364444435,0.75,1],"x":-1.29,"y":1.01},{"time":0.7334,"curve":[0.25,0,0.75,1],"x":16.04,"y":8.8},{"time":1.1667,"x":-1.29,"y":1.01}],"rotate":[{"time":0,"curve":"stepped","angle":1.23},{"time":0.6667,"curve":[0.206821024,0.364444435,0.75,1],"angle":1.23},{"time":0.7334,"curve":[0.25,0,0.75,1],"angle":6.17},{"time":1.1667,"angle":1.23}],"shear":[{"time":0,"curve":"stepped"},{"time":0.6667,"curve":[0.206821024,0.364444435,0.75,1]},{"time":0.7334,"curve":[0.25,0,0.75,1]},{"time":1.1667}]},"C_R_Shield":{"rotate":[{"time":0,"curve":[0.25,0,0.75,1],"angle":0},{"time":0.3333,"curve":"stepped","angle":16.06},{"time":0.6666,"curve":[0.259595335,0.5688889,0.5245098,0.9911111],"angle":16.06},{"time":0.6999,"curve":[0.25,0,0.75,1],"angle":24.46},{"time":0.8999,"curve":[0.576241136,0.008888889,0.855548561,1],"angle":0.27},{"time":1.1666,"angle":0}],"shear":[{"time":0,"curve":[0.25,0,0.75,1]},{"time":0.3333,"curve":"stepped"},{"time":0.6666,"curve":[0.259595335,0.5688889,0.5245098,0.9911111]},{"time":0.6999,"curve":[0.25,0,0.75,1]},{"time":0.8999,"curve":[0.576241136,0.008888889,0.855548561,1]},{"time":1.1666}]},"C_Hood_II":{"rotate":[{"time":0,"curve":"stepped","angle":-4.43},{"time":0.6667,"curve":[0.235607013,0.36,0.75,1],"angle":-4.43},{"time":0.7334,"curve":[0.25,0,0.75,1],"angle":-25.29},{"time":1.1667,"angle":-4.43}],"shear":[{"time":0,"curve":"stepped"},{"time":0.6667,"curve":[0.235607013,0.36,0.75,1]},{"time":0.7334,"curve":[0.25,0,0.75,1]},{"time":1.1667}]},"C_L_Arm":{"rotate":[{"time":0,"curve":[0.25,0,0.75,1],"angle":0.15},{"time":0.3333,"curve":[0.25,0,0.75,1],"angle":88.53},{"time":0.6666,"curve":[0.259595335,0.5688889,0.5245098,0.9911111],"angle":88.53},{"time":0.6999,"curve":[0.576241136,0.008888889,0.855548561,1],"angle":21.83},{"time":1.1666,"angle":0.15}],"shear":[{"time":0,"curve":[0.25,0,0.75,1]},{"time":0.3333,"curve":[0.25,0,0.75,1]},{"time":0.6666,"curve":[0.259595335,0.5688889,0.5245098,0.9911111]},{"time":0.6999,"curve":[0.576241136,0.008888889,0.855548561,1]},{"time":1.1666}]},"C_B_Skirt2":{"translate":[{"time":0,"x":-7.64,"y":-0.47}],"rotate":[{"time":0,"curve":"stepped","angle":1.81},{"time":0.6667,"curve":[0.269190669,0.3911111,0.75,1],"angle":1.81},{"time":0.7334,"curve":[0.25,0,0.75,1],"angle":21.57},{"time":1.1667,"angle":1.81}],"shear":[{"time":0,"curve":"stepped"},{"time":0.6667,"curve":[0.269190669,0.3911111,0.75,1]},{"time":0.7334,"curve":[0.25,0,0.75,1]},{"time":1.1667}]},"C_B_Skirt":{"rotate":[{"time":0,"angle":-2.69}],"shear":[{"time":0}]},"C_L_Hand":{"rotate":[{"time":0,"curve":[0.25,0,0.75,1],"angle":0},{"time":0.3333,"curve":"stepped","angle":-41.29},{"time":0.6666,"curve":[0.259595335,0.5688889,0.5245098,0.9911111],"angle":-41.29},{"time":0.6999,"curve":[0.25,0,0.75,1],"angle":-62.6},{"time":0.8999,"curve":[0.576241136,0.008888889,0.855548561,1],"angle":-17.12},{"time":1.1666,"angle":0}],"shear":[{"time":0,"curve":[0.25,0,0.75,1]},{"time":0.3333,"curve":"stepped"},{"time":0.6666,"curve":[0.259595335,0.5688889,0.5245098,0.9911111]},{"time":0.6999,"curve":[0.25,0,0.75,1]},{"time":0.8999,"curve":[0.576241136,0.008888889,0.855548561,1]},{"time":1.1666}]},"C_Head":{"rotate":[{"time":0,"curve":"stepped","angle":-0.66},{"time":0.6667,"curve":[0.245202333,0.5822222,0.57248646,0.9911111],"angle":-0.66},{"time":0.7334,"curve":[0.25,0,0.75,1],"angle":5.17},{"time":0.8334,"curve":[0.25,0,0.75,1],"angle":-1.89},{"time":1.1667,"angle":-0.66}],"shear":[{"time":0,"curve":"stepped"},{"time":0.6667,"curve":[0.245202333,0.5822222,0.57248646,0.9911111]},{"time":0.7334,"curve":[0.25,0,0.75,1]},{"time":0.8334,"curve":[0.25,0,0.75,1]},{"time":1.1667}]},"C_R_Skirt_I":{"rotate":[{"time":0,"curve":[0.25,0,0.75,1],"angle":7.85},{"time":0.3333,"curve":"stepped","angle":3.61},{"time":0.6666,"curve":[0.0916771,0.386666656,0.404568225,0.9866667],"angle":3.61},{"time":0.7333,"curve":[0.504276156,0.008888889,0.8219649,0.9955556],"angle":27.45},{"time":1.1666,"angle":7.85}],"shear":[{"time":0,"curve":[0.25,0,0.75,1]},{"time":0.3333,"curve":"stepped"},{"time":0.6666,"curve":[0.0916771,0.386666656,0.404568225,0.9866667]},{"time":0.7333,"curve":[0.504276156,0.008888889,0.8219649,0.9955556]},{"time":1.1666}]},"C_R_Forearm":{"translate":[{"time":0,"curve":[0.25,0,0.75,1]},{"time":0.7,"curve":[0.18763037,0.5688889,0.567688763,1]},{"time":0.7667,"curve":[0.25,0,0.75,1],"x":-1.31,"y":8.33},{"time":1.1667}],"rotate":[{"time":0,"curve":[0.25,0,0.75,1],"angle":-5.35},{"time":0.3333,"curve":[0.25,0,0.75,1],"angle":-48.51},{"time":0.4,"curve":[0.25,0,0.75,1],"angle":-43.51},{"time":0.4667,"curve":[0.25,0,0.75,1],"angle":-48.51},{"time":0.5334,"curve":[0.25,0,0.75,1],"angle":-43.51},{"time":0.6001,"curve":[0.25,0,0.75,1],"angle":-48.51},{"time":0.6668,"curve":[0.259595335,0.5688889,0.5245098,0.9911111],"angle":-43.51},{"time":0.7001,"curve":[0.18763037,0.5688889,0.567688763,1],"angle":44.19},{"time":0.7668,"curve":[0.25,0,0.75,1],"angle":51.13},{"time":1.1668,"angle":-5.35}],"shear":[{"time":0,"curve":[0.25,0,0.75,1]},{"time":0.3333,"curve":[0.25,0,0.75,1]},{"time":0.4,"curve":[0.25,0,0.75,1]},{"time":0.4667,"curve":[0.25,0,0.75,1]},{"time":0.5334,"curve":[0.25,0,0.75,1]},{"time":0.6001,"curve":[0.25,0,0.75,1]},{"time":0.6668,"curve":[0.259595335,0.5688889,0.5245098,0.9911111]},{"time":0.7001,"curve":[0.18763037,0.5688889,0.567688763,1]},{"time":0.7668,"curve":[0.25,0,0.75,1]},{"time":1.1668}]},"C_Chest":{"rotate":[{"time":0,"curve":"stepped","angle":0.74},{"time":0.6667,"curve":[0.259595335,0.5688889,0.5245098,0.9911111],"angle":0.74},{"time":0.7,"curve":[0.25,0,0.75,1],"angle":1.19},{"time":0.8333,"curve":[0.25,0,0.75,1],"angle":6.96},{"time":1.1666,"angle":0.74}],"shear":[{"time":0,"curve":"stepped"},{"time":0.6667,"curve":[0.259595335,0.5688889,0.5245098,0.9911111]},{"time":0.7,"curve":[0.25,0,0.75,1]},{"time":0.8333,"curve":[0.25,0,0.75,1]},{"time":1.1666}]},"C_L_Forearm":{"rotate":[{"time":0,"curve":[0.25,0,0.75,1],"angle":1.14},{"time":0.3333,"curve":[0.25,0,0.75,1],"angle":-35.65},{"time":0.4,"curve":[0.25,0,0.75,1],"angle":-30.65},{"time":0.4667,"curve":[0.25,0,0.75,1],"angle":-35.65},{"time":0.5334,"curve":[0.25,0,0.75,1],"angle":-30.65},{"time":0.6001,"curve":[0.25,0,0.75,1],"angle":-35.65},{"time":0.6668,"curve":[0.259595335,0.5688889,0.5245098,0.9911111],"angle":-30.65},{"time":0.7001,"curve":[0.18763037,0.5688889,0.567688763,1],"angle":64.5},{"time":0.7668,"curve":[0.25,0,0.75,1],"angle":79.17},{"time":1.1668,"angle":1.14}],"shear":[{"time":0,"curve":[0.25,0,0.75,1]},{"time":0.3333,"curve":[0.25,0,0.75,1]},{"time":0.4,"curve":[0.25,0,0.75,1]},{"time":0.4667,"curve":[0.25,0,0.75,1]},{"time":0.5334,"curve":[0.25,0,0.75,1]},{"time":0.6001,"curve":[0.25,0,0.75,1]},{"time":0.6668,"curve":[0.259595335,0.5688889,0.5245098,0.9911111]},{"time":0.7001,"curve":[0.18763037,0.5688889,0.567688763,1]},{"time":0.7668,"curve":[0.25,0,0.75,1]},{"time":1.1668}]},"C_R_Skirt_I2":{"rotate":[{"time":0,"curve":[0.25,0,0.75,1],"angle":6.96},{"time":0.3333,"curve":"stepped","angle":1.83},{"time":0.6666,"curve":[0.0916771,0.386666656,0.404568225,0.9866667],"angle":1.83},{"time":0.6999,"curve":[0.245202333,0.364444435,0.74999994,1],"angle":-15.01},{"time":0.8332,"curve":[0.504276156,0.008888889,0.8219649,0.9955556],"angle":22.01},{"time":1.1665,"angle":6.96}],"shear":[{"time":0,"curve":[0.25,0,0.75,1]},{"time":0.3333,"curve":"stepped"},{"time":0.6666,"curve":[0.0916771,0.386666656,0.404568225,0.9866667]},{"time":0.6999,"curve":[0.245202333,0.364444435,0.74999994,1]},{"time":0.8332,"curve":[0.504276156,0.008888889,0.8219649,0.9955556]},{"time":1.1665}]},"C_L_Skirt_II2":{"rotate":[{"time":0,"curve":[0.25,0,0.75,1],"angle":-1.96},{"time":0.3333,"curve":"stepped","angle":7.58},{"time":0.6666,"curve":[0.0916771,0.386666656,0.404568225,0.9866667],"angle":7.58},{"time":0.6999,"curve":[0.25,0.311111122,0.74999994,1],"angle":5.05},{"time":0.8666,"curve":[0.504276156,0.008888889,0.8219649,0.9955556],"angle":-22.79},{"time":1.1666,"angle":-1.96}],"shear":[{"time":0,"curve":[0.25,0,0.75,1]},{"time":0.3333,"curve":"stepped"},{"time":0.6666,"curve":[0.0916771,0.386666656,0.404568225,0.9866667]},{"time":0.6999,"curve":[0.25,0.311111122,0.74999994,1]},{"time":0.8666,"curve":[0.504276156,0.008888889,0.8219649,0.9955556]},{"time":1.1666}]},"C_R_Arm":{"rotate":[{"time":0,"curve":[0.25,0,0.75,1],"angle":4.27},{"time":0.3333,"curve":"stepped","angle":83.04},{"time":0.6666,"curve":[0.259595335,0.5688889,0.5245098,0.9911111],"angle":83.04},{"time":0.6999,"curve":[0.576241136,0.008888889,0.855548561,1],"angle":22.36},{"time":1.1666,"angle":4.27}],"shear":[{"time":0,"curve":[0.25,0,0.75,1]},{"time":0.3333,"curve":"stepped"},{"time":0.6666,"curve":[0.259595335,0.5688889,0.5245098,0.9911111]},{"time":0.6999,"curve":[0.576241136,0.008888889,0.855548561,1]},{"time":1.1666}]},"C_R_Skirt_II":{"rotate":[{"time":0,"curve":[0.25,0,0.75,1],"angle":3.67},{"time":0.3333,"curve":"stepped","angle":2.66},{"time":0.6666,"curve":[0.0916771,0.386666656,0.404568225,0.9866667],"angle":2.66},{"time":0.7666,"curve":[0.504276156,0.008888889,0.8219649,0.9955556],"angle":37.17},{"time":1.1666,"angle":3.67}],"shear":[{"time":0,"curve":[0.25,0,0.75,1]},{"time":0.3333,"curve":"stepped"},{"time":0.6666,"curve":[0.0916771,0.386666656,0.404568225,0.9866667]},{"time":0.7666,"curve":[0.504276156,0.008888889,0.8219649,0.9955556]},{"time":1.1666}]},"C_L_Skirt_II":{"rotate":[{"time":0,"curve":[0.25,0,0.75,1],"angle":-4.48},{"time":0.3333,"curve":"stepped","angle":-3.12},{"time":0.6666,"curve":[0.0916771,0.386666656,0.404568225,0.9866667],"angle":-3.12},{"time":0.7666,"curve":[0.504276156,0.008888889,0.8219649,0.9955556],"angle":-20.89},{"time":1.1666,"angle":-4.48}],"shear":[{"time":0,"curve":[0.25,0,0.75,1]},{"time":0.3333,"curve":"stepped"},{"time":0.6666,"curve":[0.0916771,0.386666656,0.404568225,0.9866667]},{"time":0.7666,"curve":[0.504276156,0.008888889,0.8219649,0.9955556]},{"time":1.1666}]},"Muzzle":{"translate":[{"time":0},{"time":0.1667,"curve":"stepped","x":41.18,"y":-8.37},{"time":1,"curve":[0.269190669,0.5288889,0.5580934,0.9911111],"x":41.18,"y":-8.37},{"time":1.1667}],"rotate":[{"time":0,"angle":0},{"time":0.1667,"curve":"stepped","angle":-3.66},{"time":1,"curve":[0.269190669,0.5288889,0.5580934,0.9911111],"angle":-3.66},{"time":1.1667,"angle":0}],"shear":[{"time":0},{"time":0.1667,"curve":"stepped"},{"time":1,"curve":[0.269190669,0.5288889,0.5580934,0.9911111]},{"time":1.1667}]}},"events":[{"time":0.7,"name":"OnAttack"}],"drawOrder":[{"time":0}]},"Default":{"bones":{"C_Chest":{"rotate":[{"time":0,"angle":0.74}],"shear":[{"time":0}]},"C_Hood_II":{"rotate":[{"time":0,"angle":-4.43}],"shear":[{"time":0}]},"C_L_Arm":{"rotate":[{"time":0,"angle":0.15}],"shear":[{"time":0}]},"C_Head":{"rotate":[{"time":0,"angle":-0.66}],"shear":[{"time":0}]},"C_R_Forearm":{"rotate":[{"time":0,"angle":-5.35}],"shear":[{"time":0}]},"C_B_Skirt2":{"translate":[{"time":0,"x":-7.64,"y":-0.47}],"rotate":[{"time":0,"angle":1.81}],"shear":[{"time":0}]},"C_L_Skirt_II2":{"rotate":[{"time":0,"angle":-1.96}],"shear":[{"time":0}]},"C_L_Skirt_II":{"rotate":[{"time":0,"angle":-4.48}],"shear":[{"time":0}]},"C_R_Skirt_I":{"rotate":[{"time":0,"angle":7.85}],"shear":[{"time":0}]},"C_Hood_I":{"translate":[{"time":0,"x":-1.29,"y":1.01}],"rotate":[{"time":0,"angle":1.23}],"shear":[{"time":0}]},"C_B_Skirt":{"rotate":[{"time":0,"angle":-2.69}],"shear":[{"time":0}]},"C_R_Arm":{"rotate":[{"time":0,"angle":4.27}],"shear":[{"time":0}]},"C_R_Skirt_II2":{"rotate":[{"time":0,"angle":2.47}],"shear":[{"time":0}]},"C_L_Skirt_I2":{"rotate":[{"time":0,"angle":-6.21}],"shear":[{"time":0}]},"C_R_Skirt_I2":{"rotate":[{"time":0,"angle":6.96}],"shear":[{"time":0}]},"C_R_Skirt_II":{"rotate":[{"time":0,"angle":3.67}],"shear":[{"time":0}]},"C_L_Skirt_I":{"rotate":[{"time":0,"angle":-5.99}],"shear":[{"time":0}]},"C_L_Forearm":{"rotate":[{"time":0,"angle":1.14}],"shear":[{"time":0}]},"C_Hip":{"rotate":[{"time":0,"angle":0.22}],"shear":[{"time":0}]}},"drawOrder":[{"time":0}]},"Die":{"bones":{"C_L_Skirt_I":{"rotate":[{"time":0,"curve":[0.1972257,0.48,0.706820965,1],"angle":-5.99},{"time":0.2333,"curve":[0.417918235,0,0.831560254,0.6488889],"angle":-22.09},{"time":0.5,"curve":[0.25,0,0.75,1],"angle":27.26},{"time":0.7,"curve":[0.25,0,0.75,1],"angle":23.28},{"time":0.9,"angle":27.26}],"shear":[{"time":0,"curve":[0.1972257,0.48,0.706820965,1]},{"time":0.2333,"curve":[0.417918235,0,0.831560254,0.6488889]},{"time":0.5,"curve":[0.25,0,0.75,1]},{"time":0.7,"curve":[0.25,0,0.75,1]},{"time":0.9}]},"C_R_Hand":{"rotate":[{"time":0,"curve":"stepped","angle":0},{"time":0.2333,"curve":[0.417918235,0,0.831560254,0.6488889],"angle":0},{"time":0.5,"angle":-20.71}],"shear":[{"time":0,"curve":"stepped"},{"time":0.2333,"curve":[0.417918235,0,0.831560254,0.6488889]},{"time":0.5}]},"IK_C_L_Leg":{"translate":[{"time":0,"curve":"stepped"},{"time":0.2333,"curve":[0.417918235,0,0.831560254,0.6488889]},{"time":0.5,"x":1.69,"y":36.38}],"rotate":[{"time":0,"curve":"stepped","angle":0},{"time":0.2333,"curve":[0.417918235,0,0.831560254,0.6488889],"angle":0},{"time":0.5,"angle":-98.67}],"shear":[{"time":0,"curve":"stepped"},{"time":0.2333,"curve":[0.417918235,0,0.831560254,0.6488889]},{"time":0.5}]},"IK_C_R_Leg":{"translate":[{"time":0,"curve":[0.1972257,0.48,0.706820965,1]},{"time":0.1667,"curve":"stepped"},{"time":0.2,"curve":[0.3490637,0,0.7003746,0.440422326],"x":6.04,"y":7.69},{"time":0.2333,"curve":[0.3490637,0,0.7003746,0.440422326],"x":6.04,"y":7.69},{"time":0.3333,"x":-10.22,"y":89.08},{"time":0.4,"curve":[0.434310526,0.326297224,0.7937025,0.7220756],"x":-10.22,"y":89.08},{"time":0.5,"x":-15.23,"y":206.42}],"rotate":[{"time":0,"curve":[0.1972257,0.48,0.706820965,1],"angle":0},{"time":0.2,"curve":[0.3490637,0,0.7003746,0.440422326],"angle":0},{"time":0.2333,"curve":[0.3490637,0,0.7003746,0.440422326],"angle":19.66},{"time":0.3333,"angle":19.66},{"time":0.4,"curve":[0.434310526,0.326297224,0.7937025,0.7220756],"angle":-5.4},{"time":0.5,"curve":"stepped","angle":-5.4},{"time":0.5667,"angle":-103.68}],"shear":[{"time":0,"curve":[0.1972257,0.48,0.706820965,1]},{"time":0.2,"curve":[0.3490637,0,0.7003746,0.440422326]},{"time":0.2333,"curve":[0.3490637,0,0.7003746,0.440422326]},{"time":0.3333},{"time":0.4,"curve":[0.434310526,0.326297224,0.7937025,0.7220756]},{"time":0.5,"curve":"stepped"},{"time":0.5667}]},"C_Hip":{"translate":[{"time":0,"curve":[0.1972257,0.48,0.706820965,1]},{"time":0.2333,"curve":[0.417918235,0,0.831560254,0.6488889],"y":10.86},{"time":0.5,"curve":[0.221214011,0.315555543,0.75,1],"x":-120.13},{"time":0.5667,"curve":[0.25,0,0.75,1],"x":-120.13},{"time":0.6334,"curve":[0.25,0,0.7691906,0.6933333],"x":-114.7},{"time":0.7001,"curve":[0.25,0,0.75,1],"x":-114.7},{"time":0.7668,"x":-120.13}],"rotate":[{"time":0,"curve":[0.1972257,0.48,0.706820965,1],"angle":0.22},{"time":0.2333,"curve":[0.417918235,0,0.831560254,0.6488889],"angle":7.9},{"time":0.5,"curve":[0.221214011,0.315555543,0.75,1],"angle":7.9},{"time":0.5667,"curve":[0.25,0,0.75,1],"angle":-78.47},{"time":0.6334,"curve":[0.25,0,0.7691906,0.6933333],"angle":-78.47},{"time":0.7001,"curve":[0.25,0,0.75,1],"angle":-80.34},{"time":0.7668,"angle":-80.34},{"time":0.8335,"angle":-76.68}],"shear":[{"time":0,"curve":[0.1972257,0.48,0.706820965,1]},{"time":0.2333,"curve":[0.417918235,0,0.831560254,0.6488889]},{"time":0.5,"curve":[0.221214011,0.315555543,0.75,1]},{"time":0.5667,"curve":[0.25,0,0.75,1]},{"time":0.6334,"curve":[0.25,0,0.7691906,0.6933333]},{"time":0.7001,"curve":[0.25,0,0.75,1]},{"time":0.7668},{"time":0.8335}]},"C_R_Skirt_II2":{"rotate":[{"time":0,"curve":[0.1972257,0.48,0.706820965,1],"angle":2.47},{"time":0.2333,"curve":[0.351351351,0.4,0.756756663,1],"angle":6.94},{"time":0.8333,"curve":[0.0625,0,0.9375,1],"angle":-7.57},{"time":1,"angle":-1.62}],"shear":[{"time":0,"curve":[0.1972257,0.48,0.706820965,1]},{"time":0.2333,"curve":[0.351351351,0.4,0.756756663,1]},{"time":0.8333,"curve":[0.0625,0,0.9375,1]},{"time":1}]},"C_L_Shield":{"rotate":[{"time":0,"curve":"stepped","angle":0},{"time":0.2333,"curve":[0.25,0,0.75,1],"angle":0},{"time":0.6666,"curve":[0.0625,0,0.947095325,0.927777775],"angle":13.28},{"time":0.9999,"angle":22.7}],"shear":[{"time":0,"curve":"stepped"},{"time":0.2333,"curve":[0.25,0,0.75,1]},{"time":0.6666,"curve":[0.0625,0,0.947095325,0.927777775]},{"time":0.9999}]},"C_L_Skirt_I2":{"rotate":[{"time":0,"curve":[0.1972257,0.48,0.706820965,1],"angle":-6.21},{"time":0.2333,"curve":[0.3814433,0.5454546,0.742267966,1],"angle":-5.4},{"time":0.8333,"curve":[0.0625,0,0.9375,1],"angle":-16.25},{"time":1,"angle":-10.3}],"shear":[{"time":0,"curve":[0.1972257,0.48,0.706820965,1]},{"time":0.2333,"curve":[0.3814433,0.5454546,0.742267966,1]},{"time":0.8333,"curve":[0.0625,0,0.9375,1]},{"time":1}]},"C_Hood_I":{"translate":[{"time":0,"curve":[0.1981267,0.4462745,0.612526238,0.9872549],"x":-1.29,"y":1.01},{"time":0.1,"curve":[0.25,0,0.75,1],"x":14.17,"y":7.56},{"time":0.6333,"curve":[0.2352768,0.368574679,0.612297,0.9866667],"x":6.34,"y":0.54},{"time":1,"x":-5.06,"y":-11.63}],"rotate":[{"time":0,"curve":[0.1981267,0.4462745,0.612526238,0.9872549],"angle":1.23},{"time":0.1,"curve":[0.25,0,0.75,1],"angle":5.64},{"time":0.6333,"curve":[0.2352768,0.368574679,0.612297,0.9866667],"angle":4.96},{"time":1,"angle":6.32}],"shear":[{"time":0,"curve":[0.1981267,0.4462745,0.612526238,0.9872549]},{"time":0.1,"curve":[0.25,0,0.75,1]},{"time":0.6333,"curve":[0.2352768,0.368574679,0.612297,0.9866667]},{"time":1}]},"C_Hood_II":{"rotate":[{"time":0,"curve":[0.260210276,0.332963377,0.602845669,0.6714761],"angle":-4.43},{"time":0.1333,"curve":[0.28228,0.3804627,0.6420594,0.7377893],"angle":-28.35},{"time":0.5333,"curve":[0.3619336,0.6107785,0.72200793,1],"angle":-34.64},{"time":1,"angle":9.38}],"shear":[{"time":0,"curve":[0.260210276,0.332963377,0.602845669,0.6714761]},{"time":0.1333,"curve":[0.28228,0.3804627,0.6420594,0.7377893]},{"time":0.5333,"curve":[0.3619336,0.6107785,0.72200793,1]},{"time":1}]},"C_L_Arm":{"rotate":[{"time":0,"curve":[0.1972257,0.48,0.706820965,1],"angle":0.15},{"time":0.2333,"curve":[0.317167282,0,0.7691906,0.6533333],"angle":-19.77},{"time":0.4333,"angle":42.88},{"time":0.6333,"curve":[0.0625,0,0.947095325,0.927777775],"angle":36.33},{"time":0.8666,"angle":44.59}],"shear":[{"time":0,"curve":[0.1972257,0.48,0.706820965,1]},{"time":0.2333,"curve":[0.317167282,0,0.7691906,0.6533333]},{"time":0.4333},{"time":0.6333,"curve":[0.0625,0,0.947095325,0.927777775]},{"time":0.8666}]},"C_B_Skirt2":{"translate":[{"time":0,"x":-7.64,"y":-0.47}],"rotate":[{"time":0,"curve":[0.1972257,0.48,0.706820965,1],"angle":1.81},{"time":0.2333,"curve":[0.351351351,0.4,0.756756663,1],"angle":10.01},{"time":0.8333,"curve":[0.0625,0,0.9375,1],"angle":-2.41},{"time":1,"angle":1.94}],"shear":[{"time":0,"curve":[0.1972257,0.48,0.706820965,1]},{"time":0.2333,"curve":[0.351351351,0.4,0.756756663,1]},{"time":0.8333,"curve":[0.0625,0,0.9375,1]},{"time":1}]},"C_B_Skirt":{"rotate":[{"time":0,"curve":"stepped","angle":-2.69},{"time":0.2333,"curve":[0.3576799,0.42187506,0.7024704,0.796875],"angle":-2.69},{"time":0.7,"curve":[0.25,0,0.75,1],"angle":-6.66},{"time":0.9,"angle":-2.69}],"shear":[{"time":0,"curve":"stepped"},{"time":0.2333,"curve":[0.3576799,0.42187506,0.7024704,0.796875]},{"time":0.7,"curve":[0.25,0,0.75,1]},{"time":0.9}]},"C_L_Hand":{"rotate":[{"time":0,"curve":"stepped","angle":0},{"time":0.2333,"curve":[0.25,0,0.75,1],"angle":0},{"time":0.6666,"curve":[0.0625,0,0.947095325,0.927777775],"angle":-9.41},{"time":0.9999,"angle":-22.38}],"shear":[{"time":0,"curve":"stepped"},{"time":0.2333,"curve":[0.25,0,0.75,1]},{"time":0.6666,"curve":[0.0625,0,0.947095325,0.927777775]},{"time":0.9999}]},"C_Head":{"rotate":[{"time":0,"curve":[0.1972257,0.48,0.706820965,1],"angle":-0.66},{"time":0.2333,"curve":[0.417918235,0,0.831560254,0.6488889],"angle":6.28},{"time":0.5,"curve":[0.25,0,0.75,1],"angle":28.28},{"time":0.6667,"curve":[0.0625,0,0.9375,1],"angle":17.3},{"time":0.7667,"curve":[0.25,0,0.75,1],"angle":22.4},{"time":0.8667,"angle":18.01}],"shear":[{"time":0,"curve":[0.1972257,0.48,0.706820965,1]},{"time":0.2333,"curve":[0.417918235,0,0.831560254,0.6488889]},{"time":0.5,"curve":[0.25,0,0.75,1]},{"time":0.6667,"curve":[0.0625,0,0.9375,1]},{"time":0.7667,"curve":[0.25,0,0.75,1]},{"time":0.8667}]},"C_R_Skirt_I":{"rotate":[{"time":0,"curve":[0.1972257,0.48,0.706820965,1],"angle":7.85},{"time":0.2333,"curve":[0.417918235,0,0.831560254,0.6488889],"angle":15.5},{"time":0.5,"curve":[0.25,0,0.75,1],"angle":-40.87},{"time":0.7,"curve":[0.25,0,0.75,1],"angle":-44.85},{"time":0.9,"angle":-40.87}],"shear":[{"time":0,"curve":[0.1972257,0.48,0.706820965,1]},{"time":0.2333,"curve":[0.417918235,0,0.831560254,0.6488889]},{"time":0.5,"curve":[0.25,0,0.75,1]},{"time":0.7,"curve":[0.25,0,0.75,1]},{"time":0.9}]},"C_R_Forearm":{"rotate":[{"time":0,"curve":"stepped","angle":-5.35},{"time":0.2333,"curve":[0.417918235,0,0.831560254,0.6488889],"angle":-5.35},{"time":0.5,"curve":[0.25,0,0.7883813,0.76],"angle":-14.17},{"time":0.6667,"curve":[0.0625,0,0.9375,1],"angle":-16.55},{"time":0.8,"angle":-29.87}],"shear":[{"time":0,"curve":"stepped"},{"time":0.2333,"curve":[0.417918235,0,0.831560254,0.6488889]},{"time":0.5,"curve":[0.25,0,0.7883813,0.76]},{"time":0.6667,"curve":[0.0625,0,0.9375,1]},{"time":0.8}]},"C_Chest":{"rotate":[{"time":0,"angle":0.74},{"time":0.1333,"angle":6.24},{"time":0.3333,"angle":3.38},{"time":0.5333,"curve":[0.2883813,0,0.7739883,0.697777748],"angle":-8.67},{"time":1,"angle":-14.31}],"shear":[{"time":0},{"time":0.1333},{"time":0.3333},{"time":0.5333,"curve":[0.2883813,0,0.7739883,0.697777748]},{"time":1}]},"C_L_Forearm":{"rotate":[{"time":0,"curve":[0.1972257,0.48,0.706820965,1],"angle":1.14},{"time":0.2333,"curve":[0.417918235,0,0.831560254,0.6488889],"angle":39.91},{"time":0.4333,"angle":16.4},{"time":0.6666,"curve":[0.0625,0,0.947095325,0.927777775],"angle":28.33},{"time":0.8999,"angle":13.98}],"shear":[{"time":0,"curve":[0.1972257,0.48,0.706820965,1]},{"time":0.2333,"curve":[0.417918235,0,0.831560254,0.6488889]},{"time":0.4333},{"time":0.6666,"curve":[0.0625,0,0.947095325,0.927777775]},{"time":0.8999}]},"C_R_Skirt_I2":{"rotate":[{"time":0,"curve":[0.1972257,0.48,0.706820965,1],"angle":6.96},{"time":0.2333,"curve":[0.3814433,0.5454546,0.742267966,1],"angle":4.76},{"time":0.8333,"curve":[0.0625,0,0.9375,1],"angle":-3.08},{"time":1,"angle":2.87}],"shear":[{"time":0,"curve":[0.1972257,0.48,0.706820965,1]},{"time":0.2333,"curve":[0.3814433,0.5454546,0.742267966,1]},{"time":0.8333,"curve":[0.0625,0,0.9375,1]},{"time":1}]},"C_L_Skirt_II2":{"rotate":[{"time":0,"curve":[0.1972257,0.48,0.706820965,1],"angle":-1.96},{"time":0.2333,"curve":[0.351351351,0.4,0.756756663,1],"angle":-4.52},{"time":0.8333,"curve":[0.0625,0,0.9375,1],"angle":-12},{"time":1,"angle":-6.05}],"shear":[{"time":0,"curve":[0.1972257,0.48,0.706820965,1]},{"time":0.2333,"curve":[0.351351351,0.4,0.756756663,1]},{"time":0.8333,"curve":[0.0625,0,0.9375,1]},{"time":1}]},"C_R_Arm":{"rotate":[{"time":0,"curve":[0.1972257,0.48,0.706820965,1],"angle":4.27},{"time":0.2333,"curve":[0.317167282,0,0.7691906,0.6533333],"angle":72.5},{"time":0.5,"angle":155.11}],"shear":[{"time":0,"curve":[0.1972257,0.48,0.706820965,1]},{"time":0.2333,"curve":[0.317167282,0,0.7691906,0.6533333]},{"time":0.5}]},"C_R_Skirt_II":{"rotate":[{"time":0,"curve":[0.1972257,0.48,0.706820965,1],"angle":3.67},{"time":0.2333,"curve":[0.417918235,0,0.831560254,0.6488889],"angle":12.15},{"time":0.5,"curve":[0.25,0,0.75,1],"angle":-9.52},{"time":0.7,"curve":[0.25,0,0.75,1],"angle":-13.5},{"time":0.9,"angle":-9.52}],"shear":[{"time":0,"curve":[0.1972257,0.48,0.706820965,1]},{"time":0.2333,"curve":[0.417918235,0,0.831560254,0.6488889]},{"time":0.5,"curve":[0.25,0,0.75,1]},{"time":0.7,"curve":[0.25,0,0.75,1]},{"time":0.9}]},"C_L_Skirt_II":{"rotate":[{"time":0,"curve":[0.1972257,0.48,0.706820965,1],"angle":-4.48},{"time":0.2333,"curve":[0.417918235,0,0.831560254,0.6488889],"angle":-14.22},{"time":0.5,"curve":[0.25,0,0.75,1],"angle":3.56},{"time":0.7,"curve":[0.25,0,0.75,1],"angle":-0.42},{"time":0.9,"angle":3.56}],"shear":[{"time":0,"curve":[0.1972257,0.48,0.706820965,1]},{"time":0.2333,"curve":[0.417918235,0,0.831560254,0.6488889]},{"time":0.5,"curve":[0.25,0,0.75,1]},{"time":0.7,"curve":[0.25,0,0.75,1]},{"time":0.9}]}},"drawOrder":[{"time":0}]},"Idle":{"bones":{"C_Hip":{"translate":[{"time":0,"curve":[0.31617649999999997,0.2857142685,0.7426470814999999,1]},{"time":0.1667,"curve":[0.25,0,0.75,1]},{"time":0.5,"curve":[0.25,0,0.75,1],"x":-5.87},{"time":0.6667,"curve":[0.243243247,0,0.6486487,0.6],"x":-5.87},{"time":1}],"rotate":[{"time":0,"curve":[0.31617649999999997,0.2857142685,0.7426470814999999,1],"angle":0.22},{"time":0.1667,"curve":[0.25,0,0.75,1],"angle":0.75},{"time":0.5,"curve":[0.25,0,0.75,1],"angle":0.75},{"time":0.6667,"curve":[0.243243247,0,0.6486487,0.6],"angle":-1.1},{"time":1,"angle":0.22}],"shear":[{"time":0,"curve":[0.31617649999999997,0.2857142685,0.7426470814999999,1]},{"time":0.1667,"curve":[0.25,0,0.75,1]},{"time":0.5,"curve":[0.25,0,0.75,1]},{"time":0.6667,"curve":[0.243243247,0,0.6486487,0.6]},{"time":1}]},"C_Chest":{"rotate":[{"time":0,"curve":[0.25,0,0.75,1],"angle":0.74},{"time":0.5,"curve":[0.25,0,0.75,1],"angle":2.68},{"time":1,"angle":0.74}],"shear":[{"time":0,"curve":[0.25,0,0.75,1]},{"time":0.5,"curve":[0.25,0,0.75,1]},{"time":1}]},"C_Head":{"rotate":[{"time":0,"curve":[0.38031584,0.5945948,0.726609945,1],"angle":-0.66},{"time":0.1333,"curve":[0.25,0,0.75,1],"angle":0},{"time":0.6333,"curve":[0.2424569,0,0.662715554,0.652173936],"angle":-3.23},{"time":1,"angle":-0.66}],"shear":[{"time":0,"curve":[0.38031584,0.5945948,0.726609945,1]},{"time":0.1333,"curve":[0.25,0,0.75,1]},{"time":0.6333,"curve":[0.2424569,0,0.662715554,0.652173936]},{"time":1}]},"C_R_Arm":{"rotate":[{"time":0,"curve":[0.25,0,0.75,1],"angle":4.27},{"time":0.5,"curve":[0.25,0,0.75,1],"angle":-7.08},{"time":1,"angle":4.27}],"shear":[{"time":0,"curve":[0.25,0,0.75,1]},{"time":0.5,"curve":[0.25,0,0.75,1]},{"time":1}]},"C_R_Forearm":{"rotate":[{"time":0,"curve":[0.25,0,0.75,1],"angle":-5.35},{"time":0.5,"curve":[0.25,0,0.75,1],"angle":9.96},{"time":1,"angle":-5.35}],"shear":[{"time":0,"curve":[0.25,0,0.75,1]},{"time":0.5,"curve":[0.25,0,0.75,1]},{"time":1}]},"C_R_Hand":{"rotate":[{"time":0,"curve":[0.25,0,0.75,1],"angle":0},{"time":0.5,"curve":[0.25,0,0.75,1],"angle":10.81},{"time":1,"angle":0}],"shear":[{"time":0,"curve":[0.25,0,0.75,1]},{"time":0.5,"curve":[0.25,0,0.75,1]},{"time":1}]},"C_L_Arm":{"rotate":[{"time":0,"curve":[0.382353,0.571428537,0.735294163,1],"angle":0.15},{"time":0.1667,"curve":[0.25,0,0.75,1],"angle":-2.57},{"time":0.6667,"curve":[0.243243247,0,0.6486487,0.6],"angle":6.99},{"time":1,"angle":0.15}],"shear":[{"time":0,"curve":[0.382353,0.571428537,0.735294163,1]},{"time":0.1667,"curve":[0.25,0,0.75,1]},{"time":0.6667,"curve":[0.243243247,0,0.6486487,0.6]},{"time":1}]},"C_L_Forearm":{"rotate":[{"time":0,"curve":[0.382353,0.571428537,0.735294163,1],"angle":1.14},{"time":0.1667,"curve":[0.25,0,0.75,1],"angle":3.97},{"time":0.6667,"curve":[0.243243247,0,0.6486487,0.6],"angle":-6.02},{"time":1,"angle":1.14}],"shear":[{"time":0,"curve":[0.382353,0.571428537,0.735294163,1]},{"time":0.1667,"curve":[0.25,0,0.75,1]},{"time":0.6667,"curve":[0.243243247,0,0.6486487,0.6]},{"time":1}]},"C_L_Hand":{"rotate":[{"time":0,"curve":[0.25,0,0.75,1],"angle":0},{"time":0.5,"curve":[0.25,0,0.75,1],"angle":-8.36},{"time":1,"angle":0}],"shear":[{"time":0,"curve":[0.25,0,0.75,1]},{"time":0.5,"curve":[0.25,0,0.75,1]},{"time":1}]},"C_Hood_II":{"rotate":[{"time":0,"curve":[0.351351351,0.4,0.756756663,1],"angle":-4.43},{"time":0.3333,"curve":[0.25,0,0.75,1],"angle":0},{"time":0.8333,"curve":[0.264705867,0,0.617647052,0.428571433],"angle":-6.19},{"time":1,"angle":-4.43}],"shear":[{"time":0,"curve":[0.351351351,0.4,0.756756663,1]},{"time":0.3333,"curve":[0.25,0,0.75,1]},{"time":0.8333,"curve":[0.264705867,0,0.617647052,0.428571433]},{"time":1}]},"C_L_Skirt_I":{"rotate":[{"time":0,"curve":[0.3749999,0.6153849,0.715909,1],"angle":-5.99},{"time":0.1,"curve":[0.25,0,0.75,1],"angle":-6.89},{"time":0.6,"curve":[0.242718443,0,0.6796116,0.714285731],"angle":0},{"time":1,"angle":-5.99}],"shear":[{"time":0,"curve":[0.3749999,0.6153849,0.715909,1]},{"time":0.1,"curve":[0.25,0,0.75,1]},{"time":0.6,"curve":[0.242718443,0,0.6796116,0.714285731]},{"time":1}]},"C_L_Skirt_I2":{"rotate":[{"time":0,"curve":[0.3814433,0.5454546,0.742267966,1],"angle":-6.21},{"time":0.2,"curve":[0.25,0,0.75,1],"angle":-9.83},{"time":0.7,"curve":[0.245098054,0,0.637254953,0.5555556],"angle":0},{"time":1,"angle":-6.21}],"shear":[{"time":0,"curve":[0.3814433,0.5454546,0.742267966,1]},{"time":0.2,"curve":[0.25,0,0.75,1]},{"time":0.7,"curve":[0.245098054,0,0.637254953,0.5555556]},{"time":1}]},"C_L_Skirt_II":{"rotate":[{"time":0,"curve":[0.382353,0.571428537,0.735294163,1],"angle":-4.48},{"time":0.1667,"curve":[0.25,0,0.75,1],"angle":-6.25},{"time":0.6667,"curve":[0.243243247,0,0.6486487,0.6],"angle":0},{"time":1,"angle":-4.48}],"shear":[{"time":0,"curve":[0.382353,0.571428537,0.735294163,1]},{"time":0.1667,"curve":[0.25,0,0.75,1]},{"time":0.6667,"curve":[0.243243247,0,0.6486487,0.6]},{"time":1}]},"C_L_Skirt_II2":{"rotate":[{"time":0,"curve":[0.351351351,0.4,0.756756663,1],"angle":-1.96},{"time":0.3333,"curve":[0.25,0,0.75,1],"angle":-6.9},{"time":0.8333,"curve":[0.264705867,0,0.617647052,0.428571433],"angle":0},{"time":1,"angle":-1.96}],"shear":[{"time":0,"curve":[0.351351351,0.4,0.756756663,1]},{"time":0.3333,"curve":[0.25,0,0.75,1]},{"time":0.8333,"curve":[0.264705867,0,0.617647052,0.428571433]},{"time":1}]},"C_R_Skirt_II":{"rotate":[{"time":0,"curve":[0.382353,0.571428537,0.735294163,1],"angle":3.67},{"time":0.1667,"curve":[0.25,0,0.75,1],"angle":5.13},{"time":0.6667,"curve":[0.243243247,0,0.6486487,0.6],"angle":0},{"time":1,"angle":3.67}],"shear":[{"time":0,"curve":[0.382353,0.571428537,0.735294163,1]},{"time":0.1667,"curve":[0.25,0,0.75,1]},{"time":0.6667,"curve":[0.243243247,0,0.6486487,0.6]},{"time":1}]},"C_R_Skirt_II2":{"rotate":[{"time":0,"curve":[0.351351351,0.4,0.756756663,1],"angle":2.47},{"time":0.3333,"curve":[0.25,0,0.75,1],"angle":8.72},{"time":0.8333,"curve":[0.264705867,0,0.617647052,0.428571433],"angle":0},{"time":1,"angle":2.47}],"shear":[{"time":0,"curve":[0.351351351,0.4,0.756756663,1]},{"time":0.3333,"curve":[0.25,0,0.75,1]},{"time":0.8333,"curve":[0.264705867,0,0.617647052,0.428571433]},{"time":1}]},"C_R_Skirt_I":{"rotate":[{"time":0,"curve":[0.3749999,0.6153849,0.715909,1],"angle":7.85},{"time":0.1,"curve":[0.25,0,0.75,1],"angle":9.03},{"time":0.6,"curve":[0.242718443,0,0.6796116,0.714285731],"angle":0},{"time":1,"angle":7.85}],"shear":[{"time":0,"curve":[0.3749999,0.6153849,0.715909,1]},{"time":0.1,"curve":[0.25,0,0.75,1]},{"time":0.6,"curve":[0.242718443,0,0.6796116,0.714285731]},{"time":1}]},"C_R_Skirt_I2":{"rotate":[{"time":0,"curve":[0.3814433,0.5454546,0.742267966,1],"angle":6.96},{"time":0.2,"curve":[0.25,0,0.75,1],"angle":11.01},{"time":0.7,"curve":[0.245098054,0,0.637254953,0.5555556],"angle":0},{"time":1,"angle":6.96}],"shear":[{"time":0,"curve":[0.3814433,0.5454546,0.742267966,1]},{"time":0.2,"curve":[0.25,0,0.75,1]},{"time":0.7,"curve":[0.245098054,0,0.637254953,0.5555556]},{"time":1}]},"C_B_Skirt":{"rotate":[{"time":0,"curve":[0.3814433,0.5454546,0.742267966,1],"angle":-2.69},{"time":0.2,"curve":[0.25,0,0.75,1],"angle":-2.3},{"time":0.5,"curve":"stepped","angle":-2.3},{"time":0.7,"curve":[0.245098054,0,0.637254953,0.5555556],"angle":-3.34},{"time":1,"angle":-2.69}],"shear":[{"time":0,"curve":[0.3814433,0.5454546,0.742267966,1]},{"time":0.2,"curve":[0.25,0,0.75,1]},{"time":0.5,"curve":"stepped"},{"time":0.7,"curve":[0.245098054,0,0.637254953,0.5555556]},{"time":1}]},"C_B_Skirt2":{"translate":[{"time":0,"x":-7.64,"y":-0.47}],"rotate":[{"time":0,"curve":[0.351351351,0.4,0.756756663,1],"angle":1.81},{"time":0.3333,"curve":[0.25,0,0.75,1],"angle":6.37},{"time":0.5,"curve":"stepped","angle":6.37},{"time":0.8333,"curve":[0.264705867,0,0.617647052,0.428571433],"angle":0},{"time":1,"angle":1.81}],"shear":[{"time":0,"curve":[0.351351351,0.4,0.756756663,1]},{"time":0.3333,"curve":[0.25,0,0.75,1]},{"time":0.5,"curve":"stepped"},{"time":0.8333,"curve":[0.264705867,0,0.617647052,0.428571433]},{"time":1}]},"C_R_Shield":{"translate":[{"time":0,"curve":[0.25,0,0.75,1]},{"time":0.5,"curve":[0.25,0,0.75,1],"x":-1.39,"y":1.26},{"time":1}],"rotate":[{"time":0,"curve":[0.25,0,0.75,1],"angle":0},{"time":0.5,"curve":[0.25,0,0.75,1],"angle":-9.24},{"time":1,"angle":0}],"shear":[{"time":0,"curve":[0.25,0,0.75,1]},{"time":0.5,"curve":[0.25,0,0.75,1]},{"time":1}]},"C_L_Shield":{"rotate":[{"time":0,"curve":[0.25,0,0.75,1],"angle":0},{"time":0.5,"curve":[0.25,0,0.75,1],"angle":11.07},{"time":1,"angle":0}],"shear":[{"time":0,"curve":[0.25,0,0.75,1]},{"time":0.5,"curve":[0.25,0,0.75,1]},{"time":1}]},"C_Hood_I":{"translate":[{"time":0,"curve":[0.37153047,0.519519609,0.7407559724999999,1],"x":-1.29,"y":1.01},{"time":0.1333,"curve":[0.25,0,0.75,1],"x":0.01,"y":1.28},{"time":0.3,"curve":[0.25,0,0.75,1],"x":0.01,"y":1.28},{"time":0.6333,"curve":[0.2424569,0,0.662715554,0.652173936],"x":-6.38,"y":-0.05},{"time":0.8,"curve":[0.257731944,0,0.6185567,0.4545455],"x":-6.38,"y":-0.05},{"time":1,"x":-1.29,"y":1.01}],"rotate":[{"time":0,"curve":[0.37153047,0.519519609,0.7407559724999999,1],"angle":1.23},{"time":0.1333,"curve":[0.25,0,0.75,1],"angle":1.23},{"time":0.3,"curve":[0.25,0,0.75,1],"angle":5.32},{"time":0.6333,"curve":[0.2424569,0,0.662715554,0.652173936],"angle":5.32},{"time":0.8,"curve":[0.257731944,0,0.6185567,0.4545455],"angle":-1.15},{"time":1,"angle":1.23}],"shear":[{"time":0,"curve":[0.37153047,0.519519609,0.7407559724999999,1]},{"time":0.1333,"curve":[0.25,0,0.75,1]},{"time":0.3,"curve":[0.25,0,0.75,1]},{"time":0.6333,"curve":[0.2424569,0,0.662715554,0.652173936]},{"time":0.8,"curve":[0.257731944,0,0.6185567,0.4545455]},{"time":1}]}},"drawOrder":[{"time":0}]},"Move":{"bones":{"IK_C_R_Leg":{"translate":[{"time":0,"curve":[0.25,0,0.75,1],"y":21.83},{"time":0.6667,"curve":[0.251121074,0,0.6860986499999999,0.7419354765],"y":117.11},{"time":0.8,"curve":[0.25,0,0.75,1],"y":117.11},{"time":1,"curve":[0.304387331,0.5183142,0.5504276,0.9961812],"x":22.1,"y":76.62},{"time":1.2,"curve":[0.25,0,0.75,1],"x":22.1,"y":76.62},{"time":1.3333,"y":21.83}],"rotate":[{"time":0,"curve":[0.25,0,0.75,1],"angle":0},{"time":0.6667,"curve":[0.251121074,0,0.6860986499999999,0.7419354765],"angle":0},{"time":0.8,"curve":[0.25,0,0.75,1],"angle":-22.26},{"time":1,"curve":[0.304387331,0.5183142,0.5504276,0.9961812],"angle":-22.26},{"time":1.2,"curve":[0.25,0,0.75,1],"angle":18.21},{"time":1.3333,"angle":0}],"shear":[{"time":0,"curve":[0.25,0,0.75,1]},{"time":0.6667,"curve":[0.251121074,0,0.6860986499999999,0.7419354765]},{"time":0.8,"curve":[0.25,0,0.75,1]},{"time":1,"curve":[0.304387331,0.5183142,0.5504276,0.9961812]},{"time":1.2,"curve":[0.25,0,0.75,1]},{"time":1.3333}]},"C_Hip":{"translate":[{"time":0,"curve":[0.25,0,0.75,1]},{"time":0.3,"curve":[0.25,0,0.75,1],"x":10.28},{"time":0.6667,"curve":[0.25,0,0.75,1]},{"time":1,"curve":[0.25,0,0.75,1],"x":10.28},{"time":1.3333}],"rotate":[{"time":0,"angle":0.22}],"shear":[{"time":0}]},"C_L_Forearm":{"rotate":[{"time":0,"curve":[0.25,0,0.75,1],"angle":-34.28},{"time":0.6667,"curve":[0.25,0,0.75,1],"angle":32.86},{"time":1.3334,"angle":-34.28}],"shear":[{"time":0,"curve":[0.25,0,0.75,1]},{"time":0.6667,"curve":[0.25,0,0.75,1]},{"time":1.3334}]},"C_R_Hand":{"rotate":[{"time":0,"curve":[0.37931034,0.6,0.7241379,1],"angle":-6.39},{"time":0.1667,"curve":[0.25,0,0.75,1],"angle":-11.1},{"time":0.8334,"curve":[0.24242425,0,0.6666667,0.6666667],"angle":14.43},{"time":1.3334,"angle":-6.39}],"shear":[{"time":0,"curve":[0.37931034,0.6,0.7241379,1]},{"time":0.1667,"curve":[0.25,0,0.75,1]},{"time":0.8334,"curve":[0.24242425,0,0.6666667,0.6666667]},{"time":1.3334}]},"C_R_Skirt_II2":{"rotate":[{"time":0,"curve":[0.320388347,0.2857143,0.757281542,1],"angle":12.81},{"time":0.2667,"curve":[0.25,0,0.75,1],"angle":7.7},{"time":0.3334,"curve":"stepped","angle":7.7},{"time":0.6001,"curve":[0.25,0,0.625,0.5],"angle":2.66},{"time":0.6668,"curve":"stepped","angle":2.66},{"time":0.8001,"curve":[0.375,0.5,0.75,1],"angle":-17.23},{"time":1.0001,"curve":[0.381443322,0.5454545,0.742268,1],"angle":-49.23},{"time":1.3334,"angle":12.81}],"shear":[{"time":0,"curve":[0.320388347,0.2857143,0.757281542,1]},{"time":0.2667,"curve":[0.25,0,0.75,1]},{"time":0.3334,"curve":"stepped"},{"time":0.6001,"curve":[0.25,0,0.625,0.5]},{"time":0.6668,"curve":"stepped"},{"time":0.8001,"curve":[0.375,0.5,0.75,1]},{"time":1.0001,"curve":[0.381443322,0.5454545,0.742268,1]},{"time":1.3334}]},"C_B_Skirt2":{"translate":[{"time":0,"x":-7.64,"y":-0.47}],"rotate":[{"time":0,"curve":[0.3627451,0.444444418,0.754902,1],"angle":10.04},{"time":0.2,"curve":[0.25,0,0.75,1],"angle":1.81},{"time":0.5333,"curve":[0.25,0,0.75,1],"angle":14.83},{"time":0.6666,"curve":"stepped","angle":14.83},{"time":0.8666,"curve":[0.25,0,0.75,1],"angle":1.81},{"time":1.1999,"curve":[0.257731944,0,0.6185567,0.4545455],"angle":14.83},{"time":1.3332,"angle":10.04}],"shear":[{"time":0,"curve":[0.3627451,0.444444418,0.754902,1]},{"time":0.2,"curve":[0.25,0,0.75,1]},{"time":0.5333,"curve":[0.25,0,0.75,1]},{"time":0.6666,"curve":"stepped"},{"time":0.8666,"curve":[0.25,0,0.75,1]},{"time":1.1999,"curve":[0.257731944,0,0.6185567,0.4545455]},{"time":1.3332}]},"C_Chest":{"rotate":[{"time":0,"angle":0.74}],"shear":[{"time":0}]},"C_L_Arm":{"rotate":[{"time":0,"curve":[0.25,0,0.75,1],"angle":35.72},{"time":0.6667,"curve":[0.25,0,0.75,1],"angle":-35.8},{"time":1.3334,"angle":35.72}],"shear":[{"time":0,"curve":[0.25,0,0.75,1]},{"time":0.6667,"curve":[0.25,0,0.75,1]},{"time":1.3334}]},"C_L_Shield":{"rotate":[{"time":0,"curve":[0.37931034,0.6,0.7241379,1],"angle":-2.47},{"time":0.1667,"curve":[0.25,0,0.75,1],"angle":-9.28},{"time":0.8334,"curve":[0.24242425,0,0.6666667,0.6666667],"angle":27.6},{"time":1.3334,"angle":-2.47}],"shear":[{"time":0,"curve":[0.37931034,0.6,0.7241379,1]},{"time":0.1667,"curve":[0.25,0,0.75,1]},{"time":0.8334,"curve":[0.24242425,0,0.6666667,0.6666667]},{"time":1.3334}]},"C_L_Skirt_II":{"rotate":[{"time":0,"curve":[0.3814433,0.5454546,0.742267966,1],"angle":4.24},{"time":0.1333,"curve":[0.25,0,0.75,1],"angle":4.15},{"time":0.3333,"curve":"stepped","angle":4.15},{"time":0.4666,"curve":[0.25,0,0.75,1],"angle":4.39},{"time":0.6666,"curve":"stepped","angle":4.39},{"time":0.7999,"curve":[0.25,0,0.75,1],"angle":4.15},{"time":1.1332,"curve":[0.245098054,0,0.637254953,0.5555556],"angle":4.39},{"time":1.3332,"angle":4.24}],"shear":[{"time":0,"curve":[0.3814433,0.5454546,0.742267966,1]},{"time":0.1333,"curve":[0.25,0,0.75,1]},{"time":0.3333,"curve":"stepped"},{"time":0.4666,"curve":[0.25,0,0.75,1]},{"time":0.6666,"curve":"stepped"},{"time":0.7999,"curve":[0.25,0,0.75,1]},{"time":1.1332,"curve":[0.245098054,0,0.637254953,0.5555556]},{"time":1.3332}]},"C_L_Skirt_II2":{"rotate":[{"time":0,"curve":[0.320388347,0.2857143,0.757281542,1],"angle":-16.14},{"time":0.2667,"curve":[0.25,0,0.75,1],"angle":-0.49},{"time":0.3334,"curve":"stepped","angle":-0.49},{"time":0.6001,"curve":[0.25,0,0.75,1],"angle":-18.48},{"time":0.6668,"curve":"stepped","angle":-18.48},{"time":0.9335,"curve":[0.25,0,0.75,1],"angle":-0.49},{"time":1.2668,"curve":[0.2840909,0,0.625,0.3846154],"angle":-18.48},{"time":1.3335,"angle":-16.14}],"shear":[{"time":0,"curve":[0.320388347,0.2857143,0.757281542,1]},{"time":0.2667,"curve":[0.25,0,0.75,1]},{"time":0.3334,"curve":"stepped"},{"time":0.6001,"curve":[0.25,0,0.75,1]},{"time":0.6668,"curve":"stepped"},{"time":0.9335,"curve":[0.25,0,0.75,1]},{"time":1.2668,"curve":[0.2840909,0,0.625,0.3846154]},{"time":1.3335}]},"C_R_Skirt_I":{"rotate":[{"time":0,"curve":[0.25,0,0.75,1],"angle":-0.35},{"time":0.3333,"curve":"stepped","angle":-0.35},{"time":0.4333,"curve":[0.25,0,0.75,1],"angle":-16.74},{"time":0.6666,"curve":[0.28827703,0,0.637254953,0.4577778],"angle":-19.44},{"time":0.8333,"curve":[0.364446,0.455774635,0.723003149,0.990109563],"angle":-19.52},{"time":1,"curve":[0.25,0,0.75,1],"angle":10.39},{"time":1.3333,"angle":-0.35}],"shear":[{"time":0,"curve":[0.25,0,0.75,1]},{"time":0.3333,"curve":"stepped"},{"time":0.4333,"curve":[0.25,0,0.75,1]},{"time":0.6666,"curve":[0.28827703,0,0.637254953,0.4577778]},{"time":0.8333,"curve":[0.364446,0.455774635,0.723003149,0.990109563]},{"time":1,"curve":[0.25,0,0.75,1]},{"time":1.3333}]},"C_L_Skirt_I":{"rotate":[{"time":0,"curve":[0.25,0,0.75,1],"angle":1.59},{"time":0.3333,"curve":[0.25,0,0.75,1],"angle":27.21},{"time":0.6666,"curve":[0.25,0,0.75,1],"angle":16.68},{"time":0.9999,"curve":[0.25,0,0.75,1],"angle":20.97},{"time":1.3332,"angle":1.59}],"shear":[{"time":0,"curve":[0.25,0,0.75,1]},{"time":0.3333,"curve":[0.25,0,0.75,1]},{"time":0.6666,"curve":[0.25,0,0.75,1]},{"time":0.9999,"curve":[0.25,0,0.75,1]},{"time":1.3332}]},"C_Hood_II":{"rotate":[{"time":0,"curve":[0.3814433,0.5454546,0.742267966,1],"angle":-17.7},{"time":0.1333,"curve":[0.25,0,0.75,1],"angle":-16.39},{"time":0.4666,"curve":[0.25,0,0.75,1],"angle":-19.96},{"time":0.6666,"curve":"stepped","angle":-19.96},{"time":0.7999,"curve":[0.25,0,0.75,1],"angle":-16.39},{"time":1.1332,"curve":[0.245098054,0,0.637254953,0.5555556],"angle":-19.96},{"time":1.3332,"angle":-17.7}],"shear":[{"time":0,"curve":[0.3814433,0.5454546,0.742267966,1]},{"time":0.1333,"curve":[0.25,0,0.75,1]},{"time":0.4666,"curve":[0.25,0,0.75,1]},{"time":0.6666,"curve":"stepped"},{"time":0.7999,"curve":[0.25,0,0.75,1]},{"time":1.1332,"curve":[0.245098054,0,0.637254953,0.5555556]},{"time":1.3332}]},"C_R_Arm":{"rotate":[{"time":0,"curve":[0.25,0,0.75,1],"angle":-34.3},{"time":0.6667,"curve":[0.25,0,0.75,1],"angle":28.47},{"time":1.3334,"angle":-34.3}],"shear":[{"time":0,"curve":[0.25,0,0.75,1]},{"time":0.6667,"curve":[0.25,0,0.75,1]},{"time":1.3334}]},"C_B_Skirt":{"rotate":[{"time":0,"curve":[0.381720334,0.5833332,0.7311828,1],"angle":-1.99},{"time":0.1,"curve":[0.25,0,0.75,1],"angle":-2.69},{"time":0.4333,"curve":[0.25,0,0.75,1],"angle":0.17},{"time":0.6666,"curve":"stepped","angle":0.17},{"time":0.7666,"curve":[0.25,0,0.75,1],"angle":-2.69},{"time":1.0999,"curve":[0.242718443,0,0.655339837,0.625],"angle":0.17},{"time":1.3332,"angle":-1.99}],"shear":[{"time":0,"curve":[0.381720334,0.5833332,0.7311828,1]},{"time":0.1,"curve":[0.25,0,0.75,1]},{"time":0.4333,"curve":[0.25,0,0.75,1]},{"time":0.6666,"curve":"stepped"},{"time":0.7666,"curve":[0.25,0,0.75,1]},{"time":1.0999,"curve":[0.242718443,0,0.655339837,0.625]},{"time":1.3332}]},"C_R_Forearm":{"rotate":[{"time":0,"curve":[0.25,0,0.75,1],"angle":29.58},{"time":0.6667,"curve":[0.25,0,0.75,1],"angle":-30.44},{"time":1.3334,"angle":29.58}],"shear":[{"time":0,"curve":[0.25,0,0.75,1]},{"time":0.6667,"curve":[0.25,0,0.75,1]},{"time":1.3334}]},"C_Hood_I":{"translate":[{"time":0,"curve":[0.3814433,0.5454546,0.742267966,1],"x":0.08,"y":1.58},{"time":0.1333,"curve":[0.25,0,0.75,1],"x":-1.29,"y":1.01},{"time":0.4666,"curve":[0.25,0,0.75,1],"x":2.43,"y":2.58},{"time":0.7999,"curve":[0.25,0,0.75,1],"x":-1.29,"y":1.01},{"time":1.1332,"curve":[0.245098054,0,0.637254953,0.5555556],"x":2.43,"y":2.58},{"time":1.3332,"x":0.08,"y":1.58}],"rotate":[{"time":0,"curve":[0.3814433,0.5454546,0.742267966,1],"angle":2.12},{"time":0.1333,"curve":[0.25,0,0.75,1],"angle":1.23},{"time":0.4666,"curve":[0.25,0,0.75,1],"angle":3.66},{"time":0.7999,"curve":[0.25,0,0.75,1],"angle":1.23},{"time":1.1332,"curve":[0.245098054,0,0.637254953,0.5555556],"angle":3.66},{"time":1.3332,"angle":2.12}],"shear":[{"time":0,"curve":[0.3814433,0.5454546,0.742267966,1]},{"time":0.1333,"curve":[0.25,0,0.75,1]},{"time":0.4666,"curve":[0.25,0,0.75,1]},{"time":0.7999,"curve":[0.25,0,0.75,1]},{"time":1.1332,"curve":[0.245098054,0,0.637254953,0.5555556]},{"time":1.3332}]},"C_L_Hand":{"rotate":[{"time":0,"curve":[0.37931034,0.6,0.7241379,1],"angle":2.14},{"time":0.1667,"curve":[0.25,0,0.75,1],"angle":7.89},{"time":0.8334,"curve":[0.24242425,0,0.6666667,0.6666667],"angle":-23.28},{"time":1.3334,"angle":2.14}],"shear":[{"time":0,"curve":[0.37931034,0.6,0.7241379,1]},{"time":0.1667,"curve":[0.25,0,0.75,1]},{"time":0.8334,"curve":[0.24242425,0,0.6666667,0.6666667]},{"time":1.3334}]},"C_Head":{"rotate":[{"time":0,"angle":-0.66}],"shear":[{"time":0}]},"C_R_Thigh":{"translate":[{"time":0,"curve":[0.25,0,0.75,1],"x":-17.19,"y":3.15},{"time":0.6667,"curve":[0.25,0,0.75,1],"x":2.18,"y":11.81},{"time":1.3334,"x":-17.19,"y":3.15}]},"C_L_Thigh":{"translate":[{"time":0,"curve":[0.25,0,0.75,1]},{"time":0.6667,"curve":[0.25,0,0.75,1],"x":5.24,"y":-0.02},{"time":1.3334}]},"C_L_Skirt_I2":{"rotate":[{"time":0,"curve":[0.25,0,0.75,1],"angle":4.69},{"time":0.2,"curve":[0.25,0,0.75,1],"angle":-15.15},{"time":0.6667,"curve":"stepped","angle":-15.15},{"time":0.7334,"angle":4.69}],"shear":[{"time":0,"curve":[0.25,0,0.75,1]},{"time":0.2,"curve":[0.25,0,0.75,1]},{"time":0.6667,"curve":"stepped"},{"time":0.7334}]},"C_R_Shield":{"rotate":[{"time":0,"curve":[0.37931034,0.6,0.7241379,1],"angle":12.64},{"time":0.1667,"curve":[0.25,0,0.75,1],"angle":17.78},{"time":0.8334,"curve":[0.24242425,0,0.6666667,0.6666667],"angle":-10.08},{"time":1.3334,"angle":12.64}],"shear":[{"time":0,"curve":[0.37931034,0.6,0.7241379,1]},{"time":0.1667,"curve":[0.25,0,0.75,1]},{"time":0.8334,"curve":[0.24242425,0,0.6666667,0.6666667]},{"time":1.3334}]},"IK_C_L_Leg":{"translate":[{"time":0,"curve":[0.251121074,0,0.6860986499999999,0.7419354765]},{"time":0.1333,"curve":[0.25,0,0.75,1]},{"time":0.3,"curve":[0.294792,0.509425342,0.5600229,0.9955556],"x":25.7,"y":-53.67},{"time":0.5333,"curve":[0.25,0,0.75,1],"x":25.7,"y":-53.67},{"time":0.6666,"curve":[0.25,0,0.75,1],"y":-99.3},{"time":1.3333}],"rotate":[{"time":0,"curve":[0.251121074,0,0.6860986499999999,0.7419354765],"angle":0},{"time":0.1333,"curve":[0.25,0,0.75,1],"angle":-25.71},{"time":0.3,"curve":[0.294792,0.509425342,0.5600229,0.9955556],"angle":-25.71},{"time":0.5333,"curve":[0.25,0,0.75,1],"angle":30.09},{"time":0.6666,"angle":0}],"shear":[{"time":0,"curve":[0.251121074,0,0.6860986499999999,0.7419354765]},{"time":0.1333,"curve":[0.25,0,0.75,1]},{"time":0.3,"curve":[0.294792,0.509425342,0.5600229,0.9955556]},{"time":0.5333,"curve":[0.25,0,0.75,1]},{"time":0.6666}]},"C_R_Skirt_II":{"rotate":[{"time":0,"curve":[0.3814433,0.5454546,0.742267966,1],"angle":17.71},{"time":0.1333,"curve":[0.25,0,0.75,1],"angle":15.1},{"time":0.3333,"curve":"stepped","angle":15.1},{"time":0.4666,"curve":[0.245098054,0,0.637254953,0.5555556],"angle":0.05},{"time":0.6666,"curve":[0.25,0,0.75,1],"angle":-7.75},{"time":0.9999,"curve":[0.25,0,0.831560254,0.75555557],"angle":29.65},{"time":1.3332,"angle":17.71}],"shear":[{"time":0,"curve":[0.3814433,0.5454546,0.742267966,1]},{"time":0.1333,"curve":[0.25,0,0.75,1]},{"time":0.3333,"curve":"stepped"},{"time":0.4666,"curve":[0.245098054,0,0.637254953,0.5555556]},{"time":0.6666,"curve":[0.25,0,0.75,1]},{"time":0.9999,"curve":[0.25,0,0.831560254,0.75555557]},{"time":1.3332}]},"C_R_Skirt_I2":{"rotate":[{"time":0,"curve":[0.257731944,0,0.6185567,0.4545455],"angle":2.63},{"time":0.2667,"curve":[0.3627451,0.444444418,0.754902,1],"angle":-10.44},{"time":0.3334,"curve":"stepped","angle":-10.44},{"time":0.6667,"curve":[0.28827703,0,0.637254953,0.4577778],"angle":-1.63},{"time":0.8334,"curve":[0.364446,0.455774635,0.723003149,0.990109563],"angle":-16.25},{"time":1.0001,"curve":[0.25,0,0.75,1],"angle":-50.87},{"time":1.3334,"angle":2.63}],"shear":[{"time":0,"curve":[0.257731944,0,0.6185567,0.4545455]},{"time":0.2667,"curve":[0.3627451,0.444444418,0.754902,1]},{"time":0.3334,"curve":"stepped"},{"time":0.6667,"curve":[0.28827703,0,0.637254953,0.4577778]},{"time":0.8334,"curve":[0.364446,0.455774635,0.723003149,0.990109563]},{"time":1.0001,"curve":[0.25,0,0.75,1]},{"time":1.3334}]}},"drawOrder":[{"time":0}]}},"events":{"OnAttack":{"name":"OnAttack"}}}